README.rst
setup.py
MIBEL_Downloader/REE_download.py
MIBEL_Downloader/REN_download.py
MIBEL_Downloader/__init__.py
MIBEL_Downloader/download.py
MIBEL_Downloader.egg-info/PKG-INFO
MIBEL_Downloader.egg-info/SOURCES.txt
MIBEL_Downloader.egg-info/dependency_links.txt
MIBEL_Downloader.egg-info/requires.txt
MIBEL_Downloader.egg-info/top_level.txt