Metadata-Version: 1.0
Name: MIBEL-Downloader
Version: 0.66
Summary: Downloader for MIBEL Market Prices and Load/Wind Forecasts
Home-page: http://github.com/jmfilipe/Price_Forecasts___Downloader
Author: Jorge Filipe
Author-email: jmfilipe@inesctec.pt
License: MIT
Platform: UNKNOWN
